canary_endpoint/__init__.py
canary_endpoint/canary.py
canary_endpoint/constants.py
canary_endpoint/decorators.py
canary_endpoint/mocks.py
canary_endpoint/prometheus.py
canary_endpoint/version.py
canary_endpoint/views.py
canary_endpoint/resources/__init__.py
canary_endpoint/resources/databases.py
canary_endpoint/resources/projects.py
canary_endpoint/resources/rq.py
canary_endpoint/resources/search.py
canary_endpoint/resources/services.py
django_canary_endpoint-0.3.0.dist-info/DESCRIPTION.rst
django_canary_endpoint-0.3.0.dist-info/METADATA
django_canary_endpoint-0.3.0.dist-info/metadata.json
django_canary_endpoint-0.3.0.dist-info/RECORD
django_canary_endpoint-0.3.0.dist-info/top_level.txt
django_canary_endpoint-0.3.0.dist-info/WHEEL
tests/projects/__init__.py
tests/projects/example.py
