Metadata-Version: 2.0
Name: django-canary-endpoint
Version: 0.3.0
Summary: Resource health checks for Django.
Home-page: https://github.com/TabbedOut/django-canary-endpoint
Author: TabbedOut
Author-email: dev@tabbedout.com
License: MIT License
Platform: UNKNOWN
Classifier: Environment :: Web Environment
Classifier: License :: OSI Approved :: MIT License
Requires-Dist: django-rq (>=0.7.0)
Requires-Dist: requests (>=2.0.0)
